inept/__init__.py
inept/_version.py
inept/config.py
inept/tree.py
inept/tree_builder.py
inept/types.py
inept/utils.py
inept-0.2.0.dist-info/LICENSE
inept-0.2.0.dist-info/METADATA
inept-0.2.0.dist-info/WHEEL
inept-0.2.0.dist-info/top_level.txt
inept-0.2.0.dist-info/RECORD
