Metadata-Version: 2.1
Name: inept
Version: 0.2.0
Summary: INteractive Editable oPTions
Home-page: https://github.com/brgm/inept
Author: Farid Smai
Author-email: f.smai@brgm.fr
License: GNU GPLv3
Platform: UNKNOWN
Requires-Python: >=3.6
License-File: LICENSE
Requires-Dist: click
